{
  "www.chateauversailles.fr": {
    "decouvrir": {
      "domaine": {
        "domaine-trianon": {
          "hameau-reine": {},
          "jardin-anglais": {},
          "petit-trianon": {},
          "les-jardins-francaise": {},
          "theatre-reine": {},
          "jardin-francais-petit-trianon": {}
        },
        "chateau": {
          "galerie-glaces": {},
          "grand-appartement-roi": {},
          "les-cabinets-interieurs-marie-antoinette": {},
          "grand-appartement-reine": {},
          "salle-1792": {},
          "galerie-batailles": {},
          "appartement-madame-pompadour": {},
          "salles-croisades": {},
          "appartement-dauphine": {},
          "opera-royal": {},
          "salle-congres": {},
          "attique-chimay": {},
          "galerie-histoire-chateau": {},
          "salles-louis-xiv": {},
          "salle-sacre": {},
          "les-appartements-filles-louis-xv": {},
          "appartements-filles-louis-xv": {},
          "appartement-dauphin": {},
          "chapelle-royale": {},
          "appartement-madame-barry": {},
          "salles-afrique-crimee-italie": {},
          "appartement-interieur-roi": {},
          "les-galeries-historiques": {},
          "appartement-roi": {},
          "salles-empire": {},
          "grand-commun": {}
        },
        "les-jardins": {
          "les-sculptures": {},
          "les-bassins-les-fontaines": {},
          "les-bosquets": {}
        },
        "les-jardins?field_lieu_espace_tid_selective=302": {},
        "salle-jeu-paume": {},
        "petite-ecurie": {
          "galerie-sculptures-moulages": {}
        },
        "parc": {},
        "grande-ecurie": {
          "campus-versailles": {},
          "galerie-carrosses": {},
          "academie-equestre-versailles": {}
        },
        "jardins": {
          "parterres": {}
        },
        "chateau?field_lieu_espace_tid_selective=256": {},
        "chateau?field_lieu_espace_tid_selective=270": {},
        "les-jardins?field_lieu_espace_tid_selective=303": {},
        "les-jardins?field_lieu_espace_tid_selective=301": {},
        "les-jardins?field_lieu_espace_tid_selective=All": {},
        "les-jardins?field_lieu_espace_tid_selective=304": {},
        "domaine-trianon?field_lieu_espace_tid_selective=307": {},
        "domaine-trianon?field_lieu_espace_tid_selective=305": {},
        "domaine-trianon?field_lieu_espace_tid_selective=306": {},
        "grande-ecurie?field_lieu_espace_tid_selective=310": {},
        "grande-ecurie?field_lieu_espace_tid_selective=All": {},
        "petite-ecurie?field_lieu_espace_tid_selective=All": {},
        "petite-ecurie?field_lieu_espace_tid_selective=310": {},
        "domaine-marly": {},
        "ville-versailles-cite-royale": {},
        "chateau?field_lieu_espace_tid_selective=All": {},
        "chateau?field_lieu_espace_tid_selective=257": {},
        "chateau?field_lieu_espace_tid_selective=258": {},
        "trianon": {
          "grand-trianon": {}
        },
        "domaine-trianon?field_lieu_espace_tid_selective=All": {}
      },
      "ressources": {
        "mon-petit-chateau-versailles-musique": {},
        "dessins-pour-versailles": {}
      },
      "les-collections": {},
      "les-collections?tid=320": {},
      "les-collections?tid=316": {},
      "les-collections?tid=314": {},
      "les-collections?tid=27": {},
      "les-collections?tid=28": {},
      "les-collections?tid=322": {},
      "les-collections?tid=332": {},
      "les-collections?tid=311": {},
      "les-collections?tid=All": {},
      "les-collections?tid=319": {},
      "les-ressources?page=41": {}
    },
    "preparer-ma-visite": {
      "billets-tarifs": {},
      "informations-pratiques": {},
      "conditions-gratuite": {},
      "visiter-versailles-famille": {},
      "parcours-conseils": {
        "merveilles-chateau-individuel": {},
        "art-contemporain-versailles-enfants": {},
        "galerie-carrosses-enfants": {},
        "merveilles-chateau-mobilite-reduite": {},
        "jardins-bassins-individuels": {},
        "jardins-bosquets-individuel": {},
        "trianon-chateaux-campagne-mobilite-reduite": {},
        "art-contemporain-versailles-individuel": {},
        "galerie-carrosses-mobilite-reduite": {},
        "jardins-bassins-mobilite-reduite": {},
        "jardins-bosquets-enfants": {},
        "trianon-chateaux-campagne-enfants": {},
        "merveilles-chateau-enfants": {},
        "art-contemporain-versailles-mobilite-reduite": {},
        "galerie-carrosses-individuel": {}
      },
      "faq": {},
      "sur-place": {
        "petite-venise": {},
        "flottille": {},
        "audioguide": {},
        "bornes-rechargement-mobile": {},
        "points-information": {},
        "audiophone": {},
        "toilettes-tables-langer": {},
        "consignes": {},
        "points-eau": {}
      },
      "billets-tarifs?visite-tid=1": {},
      "billets-tarifs?visite-tid=324": {},
      "billets-tarifs?visite-tid=6": {},
      "billets-tarifs?visite-tid=939": {},
      "billets-tarifs?visite-tid=2": {},
      "parcours-conseils?mois=11&public=671": {},
      "sur-place?tid=191": {},
      "sur-place?tid=190": {},
      "sur-place?tid=189": {},
      "sur-place?tid=188": {},
      "faq?tid=487": {},
      "faq?tid=194": {},
      "faq?tid=478": {},
      "faq?tid=575": {},
      "faq?tid=196": {},
      "sur-place?tid=192": {}
    },
    "actualites": {
      "actualites-mecenat": {
        "restauration-plafond-peint-salon-diane": {},
        "restauration-buffet-eau": {}
      },
      "spectacles": {
        "grandes-eaux-jardins-musicaux": {},
        "les-grandes-eaux-les-jardins-musicaux": {},
        "academie-equestre-versailles": {}
      },
      "expositions": {
        "genie-majeste-louis-xiv-bernin": {},
        "versailles-marly-sous-terre": {},
        "expositions-passees": {}
      },
      "vie-domaine": {
        "memoires-chateau": {},
        "residence-ecrivain-au-chateau": {},
        "activites-18-25-ans": {},
        "dansez-versailles": {},
        "archives-vie-domaine": {},
        "dialoguez-avec-les-sculptures-jardins-chateau-versailles": {}
      },
      "evenements": {
        "realite-virtuelle-les-jardins-disparus-roi-soleil": {},
        "evenements-passes": {},
        "ouvertures-exceptionnelles-les-weekends": {}
      },
      "agenda-chateau-versailles": {
        "fr-2025-08-21": {},
        "fr-2025-08-14": {},
        "fr-2025-08-25": {},
        "fr-2025-08-29": {},
        "fr-2025-08-17": {},
        "fr-2025-08-24": {},
        "fr-2025-08-22": {},
        "fr-2025-08-20": {},
        "fr-2025-08-23": {},
        "fr-2025-08-28": {},
        "fr-2025-08-18": {},
        "fr-2025-08-13": {},
        "fr-2025-08-26": {},
        "fr-2025-08-16": {},
        "fr-2025-08-31": {},
        "fr-2025-08-15": {},
        "fr-2025-08-27": {},
        "fr-2025-08-19": {},
        "fr-2025-08-30": {}
      }
    },
    "journee-versailles-1": {},
    "jardins-bosquets-visiteurs-situation-handicap": {},
    "journee-versailles-2": {},
    "www.onelink.to": {
      "chateau": {}
    },
    "journee-versailles-0": {},
    "journee-versailles": {},
    "jardins-bassins-visiteurs-avec-enfants": {},
    "trianon-chateaux-campagne": {}
  }
}